bbapi_toolkit/__init__.py
bbapi_toolkit/config.ini.example
bbapi_toolkit/onapi/__init__.py
bbapi_toolkit/onapi/extras.py
bbapi_toolkit/onapi/list.py
bbapi_toolkit/onapi/school_info.py
bbapi_toolkit/onapi/unpublished.py
bbapi_toolkit/onapi/academics/__init__.py
bbapi_toolkit/onapi/academics/assignments.py
bbapi_toolkit/onapi/academics/courses.py
bbapi_toolkit/onapi/academics/departments.py
bbapi_toolkit/onapi/academics/enrollment.py
bbapi_toolkit/onapi/academics/sections.py
bbapi_toolkit/onapi/admissions/__init__.py
bbapi_toolkit/onapi/admissions/candidate.py
bbapi_toolkit/onapi/athletics/__init__.py
bbapi_toolkit/onapi/athletics/location.py
bbapi_toolkit/onapi/athletics/opponent.py
bbapi_toolkit/onapi/athletics/schedule.py
bbapi_toolkit/onapi/athletics/sport.py
bbapi_toolkit/onapi/athletics/team.py
bbapi_toolkit/onapi/constituents/__init__.py
bbapi_toolkit/onapi/constituents/address.py
bbapi_toolkit/onapi/constituents/education.py
bbapi_toolkit/onapi/constituents/emergency_contacts.py
bbapi_toolkit/onapi/constituents/occupation.py
bbapi_toolkit/onapi/constituents/phone.py
bbapi_toolkit/onapi/constituents/relationship.py
bbapi_toolkit/onapi/constituents/role.py
bbapi_toolkit/onapi/constituents/user.py
bbapi_toolkit/onapi/content/__init__.py
bbapi_toolkit/onapi/content/announcements.py
bbapi_toolkit/onapi/content/events.py
bbapi_toolkit/onapi/content/news.py
bbapi_toolkit/onapi/content/photos.py
bbapi_toolkit/skyapi/__init__.py
bbapi_toolkit/skyapi/extras.py
bbapi_toolkit/skyapi/unpublished.py
bbapi_toolkit/skyapi/accounts_payable/__init__.py
bbapi_toolkit/skyapi/communication_preference/__init__.py
bbapi_toolkit/skyapi/constituent/__init__.py
bbapi_toolkit/skyapi/fundraising/__init__.py
bbapi_toolkit/skyapi/general_ledger/__init__.py
bbapi_toolkit/skyapi/gift/__init__.py
bbapi_toolkit/skyapi/opportunity/__init__.py
bbapi_toolkit/skyapi/payments/__init__.py
bbapi_toolkit/skyapi/school/__init__.py
bbapi_toolkit/skyapi/school/academics_courses.py
bbapi_toolkit-1.0.0.dist-info/LICENSE
bbapi_toolkit-1.0.0.dist-info/METADATA
bbapi_toolkit-1.0.0.dist-info/WHEEL
bbapi_toolkit-1.0.0.dist-info/top_level.txt
bbapi_toolkit-1.0.0.dist-info/RECORD
