Metadata-Version: 2.1
Name: bbapi-toolkit
Version: 1.0.0
Summary: Python package for easily accessing data via Blackbaud’s ON API and SKY API.
Author-email: "Paul C. Zimmerman" <paul@lugal.com>
License: MIT License
Project-URL: Homepage, https://github.com/Lugal-PCZ/bbapi_toolkit
Keywords: blackbaud,api
Classifier: License :: OSI Approved :: MIT License
Classifier: Programming Language :: Python
Classifier: Programming Language :: Python :: 3
Requires-Python: >=3.8
License-File: LICENSE
Requires-Dist: requests
Requires-Dist: requests-oauthlib
Requires-Dist: tomli ; python_version < "3.11"
